config/ablation_study.yml
config/all_possible_ablations.yaml
config/base_v2.yml
config/compress_class_medium.yaml
config/predict.yml
config/pretrain_large.yml
config/pretrain_medium.yml
config/pretrain_small.yml
config/pretrain_vlarge.yml
config/pretrain_xlarge.yml
config/scgpt.yml
config/others/pretrain_MLM.yml
config/others/pretrain_denoise.yml
config/others/pretrain_mvc.yml
config/others/pretrain_onlydenoise.yml
config/others/pretrain_small_2000.yml
config/others/pretrain_small_all.yml
config/others/pretrain_small_noClass.yml
config/others/pretrain_small_onlyDNS.yml
config/others/pretrain_small_onlyMLM.yml
scprint/VERSION
scprint/__init__.py
scprint/__main__.py
scprint/base.py
scprint/cli.py
scprint/model/__init__.py
scprint/model/decoders.py
scprint/model/encoders.py
scprint/model/fsq.py
scprint/model/loss.py
scprint/model/model.py
scprint/model/utils.py
scprint/tasks/__init__.py
scprint/tasks/cell_emb.py
scprint/tasks/denoise.py
scprint/tasks/gene_emb.py
scprint/tasks/grn.py
scprint/tasks/knn_smooth.py
scprint/tasks/tmfg.py
scprint/tokenizers/__init__.py
scprint/tokenizers/embedder.py
scprint/tokenizers/protein_embedder.py
scprint/trainer/__init__.py
scprint/trainer/trainer.py
scprint/utils/__init__.py
scprint/utils/get_seq.py
scprint/utils/sinkhorn.py
scprint/utils/utils.py
slurm/submit.sh
data/main/TFs.txt
scprint-2.3.5.dist-info/METADATA
scprint-2.3.5.dist-info/WHEEL
scprint-2.3.5.dist-info/entry_points.txt
scprint-2.3.5.dist-info/licenses/LICENSE
scprint-2.3.5.dist-info/RECORD
