Metadata-Version: 2.4
Name: scprint
Version: 2.3.5
Summary: scPRINT is a Large Cell Model for Gene Network Inference, Denoising and more from scRNAseq data
Project-URL: repository, https://github.com/jkobject/scPRINT
Author-email: jeremie kalfon <jkobject@gmail.com>
License-Expression: MIT
License-File: LICENSE
Keywords: GRN,foundation model,gene regulatory network,large cell model,scPRINT,scRNAseq,transformer
Requires-Python: <3.13,>=3.10
Requires-Dist: array-api-compat>=1.9.0
Requires-Dist: attridict>=0.0.9
Requires-Dist: bengrn>=1.3.0
Requires-Dist: biomart>=0.9.0
Requires-Dist: bionty>=1.0.0
Requires-Dist: biopython
Requires-Dist: contourpy>=1.3.1
Requires-Dist: d3graph>=2.5.1
Requires-Dist: docstring-parser>=0.15
Requires-Dist: einops>=0.3.0
Requires-Dist: fair-esm>=0.5.0
Requires-Dist: future>=1.0.0
Requires-Dist: gget>=0.2.0
Requires-Dist: gget>=0.29.1
Requires-Dist: grnndata>=1.1.5
Requires-Dist: gseapy>=1.1.8
Requires-Dist: h5py>=3.12.1
Requires-Dist: hdbscan>=0.8.36
Requires-Dist: hdbscan>=0.8.40
Requires-Dist: huggingface-hub>=0.10.0
Requires-Dist: hydra-core>=1.1.0
Requires-Dist: ipykernel>=6.17.0
Requires-Dist: jsonargparse>=4.0.0
Requires-Dist: lamindb[bionty,cellregistry,jupyter,zarr]==1.0.4
Requires-Dist: leidenalg>=0.10.0
Requires-Dist: lightning>=2.3.0
Requires-Dist: matplotlib==3.9.3
Requires-Dist: numba>=0.56.0
Requires-Dist: numpy>=1.24.0
Requires-Dist: owlready2>=0.36
Requires-Dist: pandas>=2.0.0
Requires-Dist: patsy>=0.5.6
Requires-Dist: pynndescent>=0.5.11
Requires-Dist: pytorch-lightning>=2.3.0
Requires-Dist: rich>=10.0.0
Requires-Dist: scdataloader==1.9.2
Requires-Dist: scib-metrics>=0.1.0
Requires-Dist: scib>=1.0.0
Requires-Dist: scikit-learn==1.6.0
Requires-Dist: scikit-misc>=0.5.0
Requires-Dist: scipy>=1.7.0
Requires-Dist: seaborn>=0.11.0
Requires-Dist: simpler-flash==1.0.7
Requires-Dist: sparse>=0.15.4
Requires-Dist: storage3<=0.11.1
Requires-Dist: tensorly>=0.6.0
Requires-Dist: torch==2.2.0
Requires-Dist: torchaudio>=0.12.0
Requires-Dist: torchdata>=0.7.1
Requires-Dist: torchmetrics==1.6.0
Requires-Dist: torchtext>=0.13.0
Requires-Dist: torchvision>=0.13.0
Requires-Dist: typeshed-client>=2.0.0
Requires-Dist: urllib3<1.27.0,>=1.26.0
Requires-Dist: wandb>=0.12.0
Provides-Extra: dev
Requires-Dist: celltypist>=0.1.1; extra == 'dev'
Requires-Dist: coverage>=7.3.2; extra == 'dev'
Requires-Dist: datamapplot>=0.4.2; extra == 'dev'
Requires-Dist: datasets>=3.0.1; extra == 'dev'
Requires-Dist: gitchangelog>=3.0.4; extra == 'dev'
Requires-Dist: louvain>=0.8.2; extra == 'dev'
Requires-Dist: mkdocs-git-authors-plugin>=0.4.0; extra == 'dev'
Requires-Dist: mkdocs-git-revision-date-localized-plugin>=1.0.0; extra == 'dev'
Requires-Dist: mkdocs-jupyter>=0.2.0; extra == 'dev'
Requires-Dist: mkdocs>=1.5.3; extra == 'dev'
Requires-Dist: mkdocstrings-python>=0.10.0; extra == 'dev'
Requires-Dist: mkdocstrings>=0.22.0; extra == 'dev'
Requires-Dist: pytest-cov>=4.1.0; extra == 'dev'
Requires-Dist: pytest>=7.4.3; extra == 'dev'
Requires-Dist: ruff>=0.6.4; extra == 'dev'
Provides-Extra: flash
Requires-Dist: triton==2.2.0; extra == 'flash'
